centroid_summarizer/__init__.py
centroid_summarizer/base.py
centroid_summarizer/centroid_bow.py
centroid_summarizer/centroid_word_embeddings.py
centroid_summarizer-0.0.5.dist-info/LICENSE
centroid_summarizer-0.0.5.dist-info/METADATA
centroid_summarizer-0.0.5.dist-info/WHEEL
centroid_summarizer-0.0.5.dist-info/top_level.txt
centroid_summarizer-0.0.5.dist-info/RECORD
