Metadata-Version: 2.1
Name: centroid-summarizer
Version: 0.0.5
Summary: Extractive text summarization using centroid distance
Home-page: https://github.com/cordelia-io/centroid-summarizer
Author: Gaetano Rossiello, Pierpaolo Basile, Giovanni Semeraro, Jakub Bartczuk, olivier-compilatio, Vinicius Monteiro, austinjp
Maintainer: austinjp
License: GPL-3.0-or-later
Platform: UNKNOWN
Classifier: Development Status :: 2 - Pre-Alpha
Classifier: Intended Audience :: Developers
Classifier: Intended Audience :: Information Technology
Classifier: Intended Audience :: Science/Research
Classifier: License :: OSI Approved :: GNU General Public License v3 or later (GPLv3+)
Classifier: Natural Language :: English
Classifier: Programming Language :: Python :: 3
Classifier: Programming Language :: Python :: 3.8
Classifier: Topic :: Text Processing
License-File: LICENSE
Requires-Dist: nltk
Requires-Dist: numpy
Requires-Dist: gensim (>=4.0.0)
Requires-Dist: setuptools
Requires-Dist: sklearn
Requires-Dist: unidecode
